model_quality_report/__init__.py
model_quality_report/experiment_base.py
model_quality_report/model_base.py
model_quality_report/model_comparison_report.py
model_quality_report/quality_metrics.py
model_quality_report/report_aggregator.py
model_quality_report/schemas.py
model_quality_report/quality_report/__init__.py
model_quality_report/quality_report/base.py
model_quality_report/quality_report/crossvalidation_timeseries.py
model_quality_report/quality_report/quality_report_error.py
model_quality_report/quality_report/regression.py
model_quality_report/splitters/__init__.py
model_quality_report/splitters/base.py
model_quality_report/splitters/random.py
model_quality_report/splitters/sorted.py
model_quality_report/splitters/temporal/__init__.py
model_quality_report/splitters/temporal/split_date.py
model_quality_report/splitters/temporal/time_delta.py
model_quality_report/splitters/temporal/cross_validation/__init__.py
model_quality_report/splitters/temporal/cross_validation/by_frequency.py
model_quality_report/splitters/temporal/cross_validation/by_horizon.py
model_quality_report/splitters/temporal/cross_validation/fixed_dates.py
model_quality_report-1.3.0.dist-info/AUTHORS.md
model_quality_report-1.3.0.dist-info/LICENSE.txt
model_quality_report-1.3.0.dist-info/METADATA
model_quality_report-1.3.0.dist-info/WHEEL
model_quality_report-1.3.0.dist-info/top_level.txt
model_quality_report-1.3.0.dist-info/RECORD
