Metadata-Version: 2.1
Name: model-quality-report
Version: 1.3.0
Summary: This packages enables a quick creation of a report comparing quality of several ML models
Home-page: https://gitlab.com/francesco-calcavecchia/model_quality_report
Author: Sebastian Angst, Stanislav Khrapov
Author-email: sebastian.angst@dbschenker.com, khrapovs@gmail.com
License: mit
Platform: any
Classifier: Development Status :: 4 - Beta
Classifier: Programming Language :: Python
Requires-Python: >=3.7
License-File: LICENSE.txt
License-File: AUTHORS.md
Requires-Dist: pandas
Requires-Dist: sklearn
Requires-Dist: pandera
Provides-Extra: deploy
Requires-Dist: wheel ; extra == 'deploy'
Requires-Dist: build ; extra == 'deploy'
Requires-Dist: twine ; extra == 'deploy'
Provides-Extra: dev
Requires-Dist: black ; extra == 'dev'
Requires-Dist: pre-commit ; extra == 'dev'
Provides-Extra: doc
Requires-Dist: mkdocs ; extra == 'doc'
Requires-Dist: pymdown-extensions ; extra == 'doc'
Provides-Extra: test
Requires-Dist: coverage ; extra == 'test'
Requires-Dist: parameterized ; extra == 'test'
